{
  "uses": "themes/dark.json",
  "theme": {
    "layout": {
      "orientation": "portrait",
      "columns": 1
    },
    "fonts": {
      "area_title": { "family": "Cormorant Garamond", "weight": "700", "size": "$hero", "color": "#ffffff" },
      "description": { "family": "DM Sans", "weight": "400", "size": "$sm", "color": "#c4e0ff", "letter_spacing": "0.16em" }
    }
  },
  "header": {
    "elements": [
      {
        "type": "text",
        "text": "ONE HARBOR PLAZA",
        "font": "description"
      }
    ]
  },
  "areas": [
    {
      "background": "linear-gradient(160deg, #1a3fc4 0%, #0a1a5e 100%)",
      "icon": "fa-solid fa-stethoscope",
      "icon_height": "30%",
      "icon_color": "#7fb8ff",
      "title": "Dr. Kayla Smith",
      "subtitle": "FAMILY MEDICINE  ·  SUITE 210",
      "align": "left",
      "valign": "bottom"
    }
  ]
}
